LICENSE
README.rst
setup.py
minio_handler/__init__.py
minio_handler/minio_handler.py
minio_handler/test_Minio_Handler_unittest.py
minio_handler.egg-info/PKG-INFO
minio_handler.egg-info/SOURCES.txt
minio_handler.egg-info/dependency_links.txt
minio_handler.egg-info/requires.txt
minio_handler.egg-info/top_level.txt